odoo9_addon_hr_employee_firstname-9.0.1.0.0-py2.7-nspkg.pth
odoo_addons/hr_employee_firstname/__openerp__.py
odoo_addons/hr_employee_firstname/__init__.py
odoo_addons/hr_employee_firstname/README.rst
odoo_addons/hr_employee_firstname/models/hr_employee.py
odoo_addons/hr_employee_firstname/models/__init__.py
odoo_addons/hr_employee_firstname/i18n/nl_NL.po
odoo_addons/hr_employee_firstname/i18n/it.po
odoo_addons/hr_employee_firstname/i18n/es.po
odoo_addons/hr_employee_firstname/i18n/ar.po
odoo_addons/hr_employee_firstname/i18n/ro.po
odoo_addons/hr_employee_firstname/i18n/sl.po
odoo_addons/hr_employee_firstname/i18n/hr_employee_firstname.pot
odoo_addons/hr_employee_firstname/i18n/de.po
odoo_addons/hr_employee_firstname/i18n/fr.po
odoo_addons/hr_employee_firstname/i18n/pt_BR.po
odoo_addons/hr_employee_firstname/i18n/fi.po
odoo_addons/hr_employee_firstname/views/hr_view.xml
odoo_addons/hr_employee_firstname/tests/test_hr_employee_firstname.py
odoo_addons/hr_employee_firstname/tests/__init__.py
odoo_addons/hr_employee_firstname/static/description/icon.png
odoo9_addon_hr_employee_firstname-9.0.1.0.0.dist-info/top_level.txt
odoo9_addon_hr_employee_firstname-9.0.1.0.0.dist-info/WHEEL
odoo9_addon_hr_employee_firstname-9.0.1.0.0.dist-info/RECORD
odoo9_addon_hr_employee_firstname-9.0.1.0.0.dist-info/metadata.json
odoo9_addon_hr_employee_firstname-9.0.1.0.0.dist-info/DESCRIPTION.rst
odoo9_addon_hr_employee_firstname-9.0.1.0.0.dist-info/METADATA
odoo9_addon_hr_employee_firstname-9.0.1.0.0.dist-info/namespace_packages.txt
